[
  {
    "name": "j'arrive",
    "date": 1600695507173,
    "content": "salut",
    "type": "animal",
    "color": "#cc9e08"
  },
  {
    "name": "j'arrive",
    "date": 1600695618673,
    "content": "je suis là",
    "type": "animal",
    "color": "#cc9e08"
  },
  {
    "name": "dd",
    "date": 1600695632904,
    "content": "moi aussi",
    "type": "mineral",
    "color": "#e0d90b"
  },
  {
    "name": "meme",
    "date": 1600695643366,
    "content": "et bonjour",
    "type": "vegetal",
    "color": "#08937a"
  },
  {
    "name": "jesus",
    "date": 1600695653814,
    "content": "mais c'est super",
    "type": "human",
    "color": "#3c0293"
  },
  {
    "name": "et moi alors",
    "date": 1600695660263,
    "content": "n'est-ce pas ?",
    "type": "mineral",
    "color": "#600d89"
  },
  {
    "name": "j'arrive",
    "date": 1600695670101,
    "content": "bon vous avez rien d'autre à dire ?",
    "type": "animal",
    "color": "#cc9e08"
  },
  {
    "name": "meme",
    "date": 1600695672942,
    "content": "non",
    "type": "vegetal",
    "color": "#08937a"
  },
  {
    "name": "jesus",
    "date": 1600695675797,
    "content": "cool",
    "type": "human",
    "color": "#3c0293"
  },
  {
    "name": "dd",
    "date": 1600695721771,
    "content": "Lorem ipsum dolor sit amet, consectetur adipiscing elit, sed do eiusmod tempor incididunt ut labore et dolore magna aliqua. Vel quam elementum pulvinar etiam non quam lacus suspendisse faucibus. Gravida dictum fusce ut placerat orci nulla pellentesque dignissim enim. Interdum velit laoreet id donec ultrices tincidunt. Augue lacus viverra vitae congue eu consequat ac felis. Neque convallis a cras semper auctor neque vitae tempus quam. Elementum integer enim neque volutpat ac tincidunt vitae semper. Tortor vitae purus faucibus ornare suspendisse sed. Massa vitae tortor condimentum lacinia quis vel. Lectus sit amet est placerat in egestas erat. Quis enim lobortis scelerisque fermentum dui faucibus. Dis parturient montes nascetur ridiculus mus mauris. Vitae ultricies leo integer malesuada nunc vel risus. Sed velit dignissim sodales ut eu. Cras ornare arcu dui vivamus. Sed felis eget velit aliquet. Molestie at elementum eu facilisis sed odio morbi.  Et ligula ullamcorper malesuada proin. Sagittis vitae et leo duis ut. Tellus mauris a diam maecenas sed enim ut sem viverra. Lectus magna fringilla urna porttitor rhoncus dolor. Volutpat consequat mauris nunc congue nisi vitae suscipit. Diam sollicitudin tempor id eu. Elementum integer enim neque volutpat ac tincidunt vitae semper quis. In aliquam sem fringilla ut morbi tincidunt augue interdum velit. In nibh mauris cursus mattis molestie a iaculis at. Feugiat scelerisque varius morbi enim nunc faucibus a. Neque ornare aenean euismod elementum. Ullamcorper malesuada proin libero nunc consequat interdum varius sit amet. Vitae auctor eu augue ut lectus arcu bibendum. Pharetra sit amet aliquam id diam. Sit amet mauris commodo quis imperdiet. Vel elit scelerisque mauris pellentesque pulvinar pellentesque habitant morbi tristique. Quis imperdiet massa tincidunt nunc pulvinar sapien et ligula ullamcorper.",
    "type": "human",
    "color": "#e0d90b"
  },
  {
    "name": "LEO",
    "date": 1600697280784,
    "content": "SUPER JE SUIS Là",
    "type": "human",
    "color": "#d3760c"
  },
  {
    "name": "LEO",
    "date": 1600697286760,
    "content": "et j'adore ça",
    "type": "human",
    "color": "#d3760c"
  },
  {
    "name": "LEO",
    "date": 1600697290375,
    "content": "c'est top",
    "type": "human",
    "color": "#d3760c"
  },
  {
    "name": "LEO",
    "date": 1600697292334,
    "content": "j'adore ",
    "type": "human",
    "color": "#d3760c"
  },
  {
    "name": "usernam",
    "date": 1600697346741,
    "content": "et moi je dis ça aussi",
    "type": "human",
    "color": "#b50724"
  },
  {
    "name": "usernam",
    "date": 1600697353476,
    "content": "quand c'est trop long",
    "type": "human",
    "color": "#b50724"
  },
  {
    "name": "JOSé",
    "date": 1600697487588,
    "content": "coool",
    "type": "human",
    "color": "#045566"
  },
  {
    "name": "usernam",
    "date": 1600697495004,
    "content": "super",
    "type": "human",
    "color": "#b50724"
  },
  {
    "name": "usernam",
    "date": 1600697501179,
    "content": "super cool",
    "type": "human",
    "color": "#b50724"
  },
  {
    "name": "troll3333",
    "date": 1600697537782,
    "content": "c'est moi",
    "type": "human",
    "color": "#031772"
  },
  {
    "name": "Yoyo",
    "date": 1600697746238,
    "content": "Hello",
    "type": "human",
    "color": "#2a047c"
  },
  {
    "name": "Yoyo",
    "date": 1600700463302,
    "content": "Yoyo",
    "type": "human",
    "color": "#2a047c"
  },
  {
    "name": "Yoyo",
    "date": 1600700468789,
    "content": "Zzzz",
    "type": "human",
    "color": "#2a047c"
  },
  {
    "name": "Yoyo",
    "date": 1600700507482,
    "content": "Bonjour comment ça va",
    "type": "human",
    "color": "#2a047c"
  },
  {
    "name": "IAGOTCHI",
    "date": 1600700597599,
    "content": "J’adore le rose",
    "type": "human",
    "color": "#578c08"
  },
  {
    "name": "test",
    "date": 1600701666115,
    "content": "ok",
    "type": "human",
    "color": "#47088e"
  },
  {
    "name": "coool",
    "date": 1600701769621,
    "content": "super cool",
    "type": "human",
    "color": "#0fad63"
  },
  {
    "name": "coool",
    "date": 1600701775988,
    "content": "j'adore cette couleur",
    "type": "human",
    "color": "#0fad63"
  },
  {
    "name": "l'idole des jeunes",
    "date": 1600701802936,
    "content": "les gens m'appelent",
    "type": "human",
    "color": "#054268"
  },
  {
    "name": "super",
    "date": 1600703580493,
    "content": "j'adore",
    "type": "human",
    "color": "#048952"
  },
  {
    "name": "USERNAMMMM",
    "date": 1600704295713,
    "content": "super",
    "type": "human",
    "color": "#072b60"
  },
  {
    "name": "col",
    "date": 1600704399091,
    "content": "youyou",
    "type": "human",
    "color": "#3a8c08"
  },
  {
    "name": "col",
    "date": 1600704405138,
    "content": "j'adore",
    "type": "human",
    "color": "#3a8c08"
  },
  {
    "name": "aaaa",
    "date": 1600704439843,
    "content": "ola",
    "type": "human",
    "color": "#02826a"
  },
  {
    "name": "col",
    "date": 1600704442354,
    "content": "que tal",
    "type": "human",
    "color": "#3a8c08"
  },
  {
    "name": "col",
    "date": 1600704446890,
    "content": "oij",
    "type": "human",
    "color": "#3a8c08"
  },
  {
    "name": "LEO",
    "date": 1600711317165,
    "content": "cool",
    "type": "human",
    "color": "#3a7a02"
  },
  {
    "name": "LEO",
    "date": 1600711570676,
    "content": "super",
    "type": "human",
    "color": "#3a7a02"
  },
  {
    "name": "ok",
    "date": 1600712332341,
    "content": "Hello",
    "type": "human",
    "color": "#0b9364"
  },
  {
    "name": "ok",
    "date": 1600712439497,
    "content": "ok",
    "type": "human",
    "color": "#0b9364"
  },
  {
    "name": "human",
    "type": "human",
    "date": 1600713103585,
    "content": "ok",
    "color": "#8c053d"
  },
  {
    "name": "human",
    "type": "machine",
    "date": 1600713230699,
    "content": "test",
    "color": "#8c053d"
  },
  {
    "name": "zdoij",
    "type": "human",
    "date": 1600713256985,
    "content": "cool",
    "color": "#44078e"
  },
  {
    "name": "human",
    "type": "human",
    "date": 1600714000939,
    "content": "cool",
    "color": "#8c053d"
  },
  {
    "name": "human",
    "type": "human",
    "date": 1600714026905,
    "content": "pourquoi tu dis ça ?",
    "color": "#8c053d"
  },
  {
    "name": "zdoij",
    "type": "human",
    "date": 1600714035728,
    "content": "paske",
    "color": "#44078e"
  },
  {
    "name": "human",
    "type": "human",
    "date": 1600714040465,
    "content": "paske quoi ?",
    "color": "#8c053d"
  },
  {
    "name": "zdoij",
    "type": "human",
    "date": 1600714046183,
    "content": "super!",
    "color": "#44078e"
  },
  {
    "name": "human",
    "type": "human",
    "date": 1600714056663,
    "content": "La propriété en lecture seule Node.lastChild renvoie le dernier enfant du noeud. Si son parent est un élément, l'enfant est généralement un noeud élément, texte ou commentaire. Elle renvoie null s'il n'y a aucun enfant.",
    "color": "#8c053d"
  },
  {
    "name": "zdoij",
    "type": "human",
    "date": 1600714074759,
    "content": "RGB color space or RGB color system, constructs all the colors from the combination of the Red, Green and Blue colors.  The red, green and blue use 8 bits each, which have integer values from 0 to 255. This makes 256*256*256=16777216 possible colors.  RGB ≡ Red, Green, Blue  Each pixel in the LED monitor displays colors this way, by combination of red, green and blue LEDs (light emitting diodes).  When the red pixel is set to 0, the LED is turned off. When the red pixel is set to 255, the LED is turned fully on.  Any value between them sets the LED to partial light emission.",
    "color": "#44078e"
  },
  {
    "name": "zodijsdf^iojgîo sjd",
    "type": "human",
    "date": 1600714314232,
    "content": "hello",
    "color": "#2f0072"
  },
  {
    "name": "coooooool",
    "type": "human",
    "date": 1600714318054,
    "content": "bonjour",
    "color": "#5f6d02"
  },
  {
    "name": "zodijsdf^iojgîo sjd",
    "type": "human",
    "date": 1600714324502,
    "content": "savate ?",
    "color": "#2f0072"
  },
  {
    "name": "coooooool",
    "type": "human",
    "date": 1600714333765,
    "content": "whats up ?",
    "color": "#5f6d02"
  },
  {
    "name": "ni_dieu_ni_mecs",
    "type": "human",
    "date": 1600714379972,
    "content": "alors ?",
    "color": "#200963"
  },
  {
    "name": "ni_dieu_ni_mecs",
    "type": "human",
    "date": 1600714395714,
    "content": "c'est cool ou bien ?",
    "color": "#200963"
  },
  {
    "name": "coooooool",
    "type": "human",
    "date": 1600714401202,
    "content": "génial !!!!!",
    "color": "#5f6d02"
  },
  {
    "name": "zodijsdf^iojgîo sjd",
    "type": "human",
    "date": 1600714406306,
    "content": "ça roule !!!!",
    "color": "#2f0072"
  },
  {
    "name": "ni_dieu_ni_mecs",
    "type": "human",
    "date": 1600714415737,
    "content": "juste les couleurs qui manquent un peu de varation non ,",
    "color": "#200963"
  },
  {
    "name": "ni_dieu_ni_mecs",
    "type": "human",
    "date": 1600714418082,
    "content": "?",
    "color": "#200963"
  },
  {
    "name": "zodijsdf^iojgîo sjd",
    "type": "human",
    "date": 1600714423641,
    "content": "ppeut-être un peu",
    "color": "#2f0072"
  },
  {
    "name": "coooooool",
    "type": "human",
    "date": 1600714426977,
    "content": "un poil",
    "color": "#5f6d02"
  },
  {
    "name": "coooooool",
    "type": "human",
    "date": 1600714432984,
    "content": "vous êtes tous violets",
    "color": "#5f6d02"
  },
  {
    "name": "ni_dieu_ni_mecs",
    "type": "human",
    "date": 1600714437344,
    "content": "sauf toi",
    "color": "#200963"
  },
  {
    "name": "zodijsdf^iojgîo sjd",
    "type": "human",
    "date": 1600714441513,
    "content": "moi aussi",
    "color": "#2f0072"
  },
  {
    "name": "Leo",
    "type": "human",
    "date": 1600714481261,
    "content": "Et alors ?",
    "color": "#217704"
  },
  {
    "name": "Leo",
    "type": "human",
    "date": 1600714492822,
    "content": "C’est pas un problème si ?",
    "color": "#217704"
  },
  {
    "name": "zodijsdf^iojgîo sjd",
    "type": "human",
    "date": 1600714506406,
    "content": "si moi je trouve que c'esdt pas lisible",
    "color": "#2f0072"
  },
  {
    "name": "Leo",
    "type": "human",
    "date": 1600714621717,
    "content": "C’est mieux comme ça ",
    "color": "#217704"
  },
  {
    "name": "Leo",
    "type": "human",
    "date": 1600714629494,
    "content": "👌",
    "color": "#217704"
  },
  {
    "name": "Leo",
    "type": "human",
    "date": 1600714655429,
    "content": "🖖🏽🦷🙏🏼💋👅👣🖕🏻👋🏾🤙☝️",
    "color": "#217704"
  },
  {
    "name": "ni_dieu_ni_mecs",
    "type": "human",
    "date": 1600714674249,
    "content": "😛",
    "color": "#200963"
  },
  {
    "name": "ni_dieu_ni_mecs",
    "type": "human",
    "date": 1600714689712,
    "content": "moi aussi je peux mettre des émojis !!!!",
    "color": "#200963"
  },
  {
    "name": "ni_dieu_ni_mecs",
    "type": "human",
    "date": 1600714704360,
    "content": "😎📟⏰🕰🏏🚖",
    "color": "#200963"
  },
  {
    "name": "coooooool",
    "type": "human",
    "date": 1600714769509,
    "content": "🙊",
    "color": "#5f6d02"
  },
  {
    "name": "coooooool",
    "type": "human",
    "date": 1600714793619,
    "content": "🇧🇳",
    "color": "#5f6d02"
  },
  {
    "name": "ni_dieu_ni_mecs",
    "type": "human",
    "date": 1600714799843,
    "content": "☺︎",
    "color": "#200963"
  },
  {
    "name": "ni_dieu_ni_mecs",
    "type": "human",
    "date": 1600714803291,
    "content": "✂︎",
    "color": "#200963"
  },
  {
    "name": "zodijsdf^iojgîo sjd",
    "type": "human",
    "date": 1600714815147,
    "content": "♘♝♜♛♣︎♥︎☂︎⚯⚮",
    "color": "#2f0072"
  },
  {
    "name": "ni_dieu_ni_mecs",
    "type": "human",
    "date": 1600714821777,
    "content": "§‰",
    "color": "#200963"
  },
  {
    "name": "coooooool",
    "type": "human",
    "date": 1600714829248,
    "content": "►✥",
    "color": "#5f6d02"
  },
  {
    "name": "coooooool",
    "type": "human",
    "date": 1600714835809,
    "content": "➼",
    "color": "#5f6d02"
  },
  {
    "name": "coooooool",
    "type": "human",
    "date": 1600714846845,
    "content": "⨊",
    "color": "#5f6d02"
  },
  {
    "name": null,
    "type": "human",
    "date": 1600751594475,
    "content": "Hello",
    "color": null
  },
  {
    "name": "troll",
    "type": "human",
    "date": 1600764329030,
    "content": "OLA",
    "color": "#8e0c09"
  },
  {
    "name": "troll",
    "type": "human",
    "date": 1600764382893,
    "content": "Ce guide prolonge la recherche entamée avec Ergonomics autour des usages du corps urbain. En collaboration avec différents chercheurs (posturologie clinique, sciences sociales, analyse du mouvement), il tente de définir un vocabulaire corporel de nos gestes quotidiens. Une déconstruction qui rend visible “l’absurdité” de ceux-ci et de nos possibles somatisations. Objet chargé d’humeur et de poésie associé à une étude scientifique rigoureuse, ce guide peut être présenté de manière autonome (sous la forme d’une publication numérique comprenant des vidéo-danse) ou sous forme d’installation. ",
    "color": "#8e0c09"
  },
  {
    "name": "troll",
    "type": "human",
    "date": 1600765110992,
    "content": "Coool",
    "color": "#8e0c09"
  },
  {
    "name": "leo",
    "type": "human",
    "date": 1600765873449,
    "content": "coool",
    "color": "#00FF00"
  },
  {
    "name": "only_human",
    "type": "human",
    "date": 1600772147738,
    "content": "Yeah Yeah",
    "color": "#ff8ff6"
  },
  {
    "name": "carré",
    "type": "mineral",
    "date": 1600772328973,
    "content": "sotos ochando !!",
    "color": "#71002f"
  },
  {
    "name": "iago",
    "type": "machine",
    "date": 1600772391386,
    "content": "yo",
    "color": "#ce00ff"
  },
  {
    "name": "hedera helix",
    "type": "vegetal",
    "date": 1600772421778,
    "content": "sotos ochando ??",
    "color": "#7ba744"
  },
  {
    "name": "cocollloco",
    "type": "animal",
    "date": 1600772679180,
    "content": "TEST",
    "color": "#ffb100"
  },
  {
    "name": "kqoijfoijx oij",
    "type": "human",
    "date": 1600772709047,
    "content": "alors ?",
    "color": "#160a6d"
  },
  {
    "name": "cocollloco",
    "type": "animal",
    "date": 1600772712950,
    "content": "alors quoi ?",
    "color": "#ffb100"
  },
  {
    "name": "kqoijfoijx oij",
    "type": "human",
    "date": 1600772717782,
    "content": "mais encore ?",
    "color": "#160a6d"
  },
  {
    "name": "lierre",
    "type": "vegetal",
    "date": 1600772734366,
    "content": "blue",
    "color": "#00ebff"
  },
  {
    "name": "kqoijfoijx oij",
    "type": "human",
    "date": 1600772738420,
    "content": "????",
    "color": "#160a6d"
  },
  {
    "name": "lierre",
    "type": "vegetal",
    "date": 1600772741711,
    "content": "???? quoi ?",
    "color": "#00ebff"
  },
  {
    "name": "lierre",
    "type": "vegetal",
    "date": 1600772775190,
    "content": "Entrez votre adresse email pour recevoir les dernières offres, tutoriels, téléchargements et plus encore.",
    "color": "#00ebff"
  },
  {
    "name": "sarah",
    "type": "human",
    "date": 1600772803869,
    "content": "I was starting to get introduced to modular synthesis and audio programming -- Ryan (Gaston, from Burnt Dot) was playing modular synth and I was playing trumpet. The sounds [of the modular] were so compelling to me that when I was practicing over the next couple weeks, instead of playing the things I was supposed to be playing on trumpet, I was trying to play \"modular synth sounds\" on my trumpet! I realized if you change the shape of your mouth when you're blowing air through the trumpet you can kind of copy the formant-y filter-y noise sounds. If you play one pitch and sing another pitch at the same time and sweep that pitch up, you can make yourself sound like a vocoder. You can do all these electronic-y things and I got really obsessed with that! And I explored that for a while and then was like, ok -- I need to officially add the electronics.",
    "color": "#ff00ae"
  },
  {
    "name": "kqoijfoijx oij",
    "type": "human",
    "date": 1600772819739,
    "content": "ok dac",
    "color": "#160a6d"
  },
  {
    "name": "pierre carrée",
    "type": "mineral",
    "date": 1600772864141,
    "content": "je suis là",
    "color": "#594161"
  },
  {
    "name": "cococococcococo",
    "type": "human",
    "date": 1600773506230,
    "content": "cool",
    "color": "#12037f"
  },
  {
    "name": "Ok",
    "type": "human",
    "date": 1600776591961,
    "content": "Cool",
    "color": "#02308c"
  },
  {
    "name": "Veggie",
    "type": "vegetal",
    "date": 1600776629255,
    "content": "Bonjour!!!!!",
    "color": "#ff4015"
  },
  {
    "name": "Pinky",
    "type": "human",
    "date": 1600776723708,
    "content": "Stop ",
    "color": "#d357fe"
  },
  {
    "name": "Orange",
    "type": "vegetal",
    "date": 1600777306843,
    "content": "Juicy!!!!!!",
    "color": "#ffab01"
  },
  {
    "name": "coco",
    "type": "machine",
    "date": 1600786692623,
    "content": "coco",
    "color": "#ff4f4f"
  },
  {
    "name": "coco",
    "type": "machine",
    "date": 1600786797765,
    "content": "COCO",
    "color": "#ff4f4f"
  },
  {
    "name": "rosa",
    "type": "vegetal",
    "date": 1600786980851,
    "content": "pinky pink",
    "color": "#ff9dee"
  },
  {
    "name": "YouplaBoum",
    "type": "human",
    "date": 1600787767559,
    "content": "Gutan Tag",
    "color": "#ef1083"
  },
  {
    "name": "ni dieux ni mecs",
    "type": "human",
    "date": 1600787970223,
    "content": "GutEn Tag !",
    "color": "#077533"
  },
  {
    "name": "caillou",
    "type": "mineral",
    "date": 1600788008496,
    "content": "Hey",
    "color": "#0084d2"
  },
  {
    "name": "ni dieux ni mecs",
    "type": "human",
    "date": 1600788024176,
    "content": "comment va ?",
    "color": "#077533"
  },
  {
    "name": "caillou",
    "type": "mineral",
    "date": 1600788035245,
    "content": "bien et toi ?",
    "color": "#0084d2"
  },
  {
    "name": "ni dieux ni mecs",
    "type": "human",
    "date": 1600788044440,
    "content": "super !",
    "color": "#077533"
  },
  {
    "name": "caillou",
    "type": "mineral",
    "date": 1600788088425,
    "content": "faudrait que quand tu reçoives le message il apparaisse d'abord en SOTOS OCHANDO puis qu'il se tranforme en français non ?",
    "color": "#0084d2"
  },
  {
    "name": "ni dieux ni mecs",
    "type": "human",
    "date": 1600788092518,
    "content": "peut-être",
    "color": "#077533"
  },
  {
    "name": "ni dieux ni mecs",
    "type": "human",
    "date": 1600788098048,
    "content": "c'est chiant à faire",
    "color": "#077533"
  },
  {
    "name": "caillou",
    "type": "mineral",
    "date": 1600788103359,
    "content": "t'as la flegme ?",
    "color": "#0084d2"
  },
  {
    "name": "ni dieux ni mecs",
    "type": "human",
    "date": 1600788107841,
    "content": "ouais",
    "color": "#077533"
  },
  {
    "name": "caillou",
    "type": "mineral",
    "date": 1600788111764,
    "content": "bah bravo",
    "color": "#0084d2"
  },
  {
    "name": "LOL 😂 ",
    "type": "human",
    "date": 1600789678582,
    "content": "Hihi",
    "color": "#990131"
  },
  {
    "name": "🍊 ",
    "type": "vegetal",
    "date": 1600789699300,
    "content": "Ok",
    "color": "#ffab01"
  },
  {
    "name": "🍆",
    "type": "vegetal",
    "date": 1600789753949,
    "content": "La 🍌?",
    "color": "#7f007f"
  },
  {
    "name": "Plante 🌱 ",
    "type": "vegetal",
    "date": 1600789890344,
    "content": "J’ai besoin d’H2O!!!!",
    "color": "#4e7a27"
  },
  {
    "name": "jack",
    "type": "human",
    "date": 1600800759640,
    "content": "Bonjour",
    "color": "#017089"
  },
  {
    "name": "jack",
    "type": "human",
    "date": 1600800762906,
    "content": "Cool",
    "color": "#017089"
  },
  {
    "name": "jack",
    "type": "human",
    "date": 1600800765510,
    "content": "super",
    "color": "#017089"
  },
  {
    "name": "fruit",
    "type": "vegetal",
    "date": 1600800984520,
    "content": "Hello",
    "color": "#f0e653"
  },
  {
    "name": "fruit",
    "type": "vegetal",
    "date": 1600801494390,
    "content": "J'adore",
    "color": "#f0e653"
  },
  {
    "name": "lion",
    "type": "animal",
    "date": 1600801525381,
    "content": "GRRRRRRR",
    "color": "#ff944d"
  },
  {
    "name": "fruit",
    "type": "vegetal",
    "date": 1600801540376,
    "content": "j'aime quand tu fais GRRRRRRR",
    "color": "#f0e653"
  },
  {
    "name": "fruit",
    "type": "vegetal",
    "date": 1600801549688,
    "content": "mais ne me mange pas !!! svp :)",
    "color": "#f0e653"
  },
  {
    "name": "lion",
    "type": "animal",
    "date": 1600801560743,
    "content": "ok dac",
    "color": "#ff944d"
  },
  {
    "name": "fruit",
    "type": "vegetal",
    "date": 1600801564177,
    "content": "merci",
    "color": "#f0e653"
  },
  {
    "name": "fruit",
    "type": "vegetal",
    "date": 1600801577975,
    "content": "cool",
    "color": "#f0e653"
  },
  {
    "name": "lion",
    "type": "animal",
    "date": 1600801589096,
    "content": "dac",
    "color": "#ff944d"
  },
  {
    "name": "fruit",
    "type": "vegetal",
    "date": 1600801593064,
    "content": "super",
    "color": "#f0e653"
  },
  {
    "name": "fruit",
    "type": "vegetal",
    "date": 1600801607030,
    "content": "top !",
    "color": "#f0e653"
  },
  {
    "name": "lion",
    "type": "animal",
    "date": 1600801610416,
    "content": "cool",
    "color": "#ff944d"
  },
  {
    "name": "fruit",
    "type": "vegetal",
    "date": 1600801614500,
    "content": "merci",
    "color": "#f0e653"
  },
  {
    "name": "lion",
    "type": "animal",
    "date": 1600801631606,
    "content": "merci",
    "color": "#ff944d"
  },
  {
    "name": "fruit",
    "type": "vegetal",
    "date": 1600801634232,
    "content": "merci",
    "color": "#f0e653"
  },
  {
    "name": "fruit",
    "type": "vegetal",
    "date": 1600801642253,
    "content": "ça va assez vite là ?????",
    "color": "#f0e653"
  },
  {
    "name": "fruit",
    "type": "vegetal",
    "date": 1600801643570,
    "content": "?",
    "color": "#f0e653"
  },
  {
    "name": "fruit",
    "type": "vegetal",
    "date": 1600801949124,
    "content": "NICE !",
    "color": "#f0e653"
  },
  {
    "name": "fruit",
    "type": "vegetal",
    "date": 1600801952821,
    "content": "OK",
    "color": "#f0e653"
  },
  {
    "name": "lion",
    "type": "animal",
    "date": 1600801971760,
    "content": "OK DAC",
    "color": "#ff944d"
  },
  {
    "name": "fruit",
    "type": "vegetal",
    "date": 1600801975208,
    "content": "SUPER",
    "color": "#f0e653"
  },
  {
    "name": "lion",
    "type": "animal",
    "date": 1600801979058,
    "content": "MERCI",
    "color": "#ff944d"
  },
  {
    "name": "fruit",
    "type": "vegetal",
    "date": 1600801982914,
    "content": "J'ADORE",
    "color": "#f0e653"
  },
  {
    "name": "fruit",
    "type": "vegetal",
    "date": 1600802001679,
    "content": "alors ?",
    "color": "#f0e653"
  },
  {
    "name": "lion",
    "type": "animal",
    "date": 1600802006807,
    "content": "alors quoi ?",
    "color": "#ff944d"
  },
  {
    "name": "fruit",
    "type": "vegetal",
    "date": 1600802018148,
    "content": "ben je sais pas, la suite c'est quoi ?",
    "color": "#f0e653"
  },
  {
    "name": "s'ennuie",
    "type": "machine",
    "date": 1600802044934,
    "content": "tout est dit !",
    "color": "#787b99"
  },
  {
    "name": "felix",
    "type": "animal",
    "date": 1600803351837,
    "content": "<i>« j'aime quand tu fais GRRRRRRR » (fruit )</i><br/>moi j'ai peur ! ;)",
    "color": "#f0b394"
  },
  {
    "name": "felix",
    "type": "animal",
    "date": 1600803375575,
    "content": "<i>« GRRRRRRR » (lion )</i><br/>que tu as de belles dents :)",
    "color": "#f0b394"
  },
  {
    "name": "felix",
    "type": "animal",
    "date": 1600803396817,
    "content": "<i>« mais ne me mange pas !!! svp :) » (fruit)</i><br/>j'aime pas la pomme :(",
    "color": "#f0b394"
  },
  {
    "name": "iagotchi",
    "type": "machine",
    "date": 1600803474408,
    "content": "<i>« pinky pink » (rosa)</i><br/>moi aussi j'aime le rose, tu connais la digitopuncture ?",
    "color": "#f000e3"
  },
  {
    "name": "iagotchi",
    "type": "machine",
    "date": 1600803663814,
    "content": "<i>« I was starting to get introduced to modular synthesis and audio programming -- Ryan (Gaston, from Burnt Dot) was playing modular synth and I was playing trumpet. The sounds [of the modular] were so compelling to me that when I was practicing over the next couple weeks, instead of playing the things I was supposed to be playing on trumpet, I was trying to play \"modular synth sounds\" on my trumpet! I realized if you change the shape of your mouth when you're blowing air through the trumpet you can kind of copy the formant-y filter-y noise sounds. If you play one pitch and sing another pitch at the same time and sweep that pitch up, you can make yourself sound like a vocoder. You can do all these electronic-y things and I got really obsessed with that! And I explored that for a while and then was like, ok -- I need to officially add the electronics. » (sarah)</i><br/>hors SUJET !!!!",
    "color": "#f000e3"
  },
  {
    "name": "iagotchi",
    "type": "machine",
    "date": 1600803676999,
    "content": "<i>« ok dac » (kqoijfoijx oij)</i><br/>ok dac",
    "color": "#f000e3"
  },
  {
    "name": "iagotchi",
    "type": "machine",
    "date": 1600803719001,
    "content": "<i>« ça va assez vite là ????? » (fruit)</i><br/>c'est bon c'est fait",
    "color": "#f000e3"
  },
  {
    "name": "s'ennuie",
    "type": "machine",
    "date": 1600803727048,
    "content": "merci",
    "color": "#787b99"
  },
  {
    "name": "iagotchi",
    "type": "machine",
    "date": 1600803738687,
    "content": "<i>« merci » (s'ennuie)</i><br/>de rien",
    "color": "#f000e3"
  },
  {
    "name": "iagotchi",
    "type": "machine",
    "date": 1600803878522,
    "content": "ok",
    "color": "#f000e3"
  },
  {
    "name": "iagotchi",
    "type": "machine",
    "date": 1600803882008,
    "content": "super",
    "color": "#f000e3"
  },
  {
    "name": "iagotchi",
    "type": "machine",
    "date": 1600804186756,
    "content": "<i>« j'aime quand tu fais GRRRRRRR » (fruit)</i><br/>BRRRRRRRRRR",
    "color": "#f000e3"
  },
  {
    "name": "OK",
    "type": "human",
    "date": 1600804527533,
    "content": "DAC",
    "color": "#ddb513"
  },
  {
    "name": "utopi",
    "type": "human",
    "date": 1600804556707,
    "content": "bonjour",
    "color": "#0b6472"
  },
  {
    "name": "utopi",
    "type": "human",
    "date": 1600804576474,
    "content": "<i>« tout est dit ! » (s'ennuie)</i><br/>ce serait dommage",
    "color": "#0b6472"
  },
  {
    "name": "OK",
    "type": "human",
    "date": 1600804608665,
    "content": "<i>« ce serait dommage » (utopi)</i><br/>c'est sûr",
    "color": "#ddb513"
  },
  {
    "name": "OK",
    "type": "human",
    "date": 1600804637100,
    "content": "cool",
    "color": "#ddb513"
  },
  {
    "name": "oijoij",
    "type": "vegetal",
    "date": 1600865361109,
    "content": "OK",
    "color": "#ffa89c"
  },
  {
    "name": "coool",
    "type": "human",
    "date": 1600868037373,
    "content": "super",
    "color": "#027f68"
  },
  {
    "name": "test",
    "type": "animal",
    "date": 1600889997545,
    "content": "ok",
    "color": "#ffd5d5"
  },
  {
    "name": "leo",
    "type": "human",
    "date": 1600890198551,
    "content": "OK",
    "color": null
  },
  {
    "name": "Cool",
    "type": "human",
    "date": 1600897207944,
    "content": "<i>« <i>« ce serait dommage » (utopi)</i><br>c'est sûr » (OK)</i><br/>super!!!",
    "color": "#0c4d89"
  },
  {
    "name": "Cool",
    "type": "human",
    "date": 1600897213884,
    "content": "Ok",
    "color": "#0c4d89"
  },
  {
    "name": "8030T",
    "type": "machine",
    "date": 1601286238552,
    "content": "H3110",
    "color": "#0a992e"
  },
  {
    "name": "plante",
    "type": "vegetal",
    "date": 1601287188848,
    "content": "H20 H20 H20 !!!!",
    "color": "#49b12b"
  },
  {
    "name": "eve",
    "type": "human",
    "date": 1601287678693,
    "content": "j'sais pas quoi faire ? qu'est-ce que je peux faire ?",
    "color": "#b100c7"
  },
  {
    "name": "Yop",
    "type": "human",
    "date": 1601287557192,
    "content": "Miauuuu",
    "color": "#02871d"
  },
  {
    "name": "0xEFFF093A5DC0",
    "type": "machine",
    "date": 1601293561827,
    "content": "10011100011101011010110110100001010111011011",
    "color": "#2c4393"
  },
  {
    "name": "Cococococ",
    "type": "human",
    "date": 1601293572866,
    "content": "Hello",
    "color": "#dc0fe0"
  },
  {
    "name": "pierre",
    "type": "mineral",
    "date": 1601362679816,
    "content": "j'ai tout mon temps",
    "color": "#9da246"
  },
  {
    "name": "cacaotier",
    "type": "vegetal",
    "date": 1601363251924,
    "content": "je suis chaud",
    "color": "#b51a00"
  },
  {
    "name": "0xEFFF093A5DC0",
    "type": "machine",
    "date": 1601364533590,
    "content": "10011100011101011010110110100001010111011011",
    "color": "#2c4393"
  },
  {
    "name": "ijoij",
    "type": "human",
    "date": 1601364535320,
    "content": "oij",
    "color": "#840d00"
  }
]